<?xml version="1.0" encoding="utf-8" ?>
<dwsync>
<file name="reset.css" server="O:/intra/portfolio/" local="131816526365572761" remote="131816526360000000" Dst="2" />
<file name="layout.css" server="O:/intra/portfolio/" local="131872702627170483" remote="131872666620000000" Dst="2" />
<file name="index.html" server="O:/intra/portfolio/" local="131872702627030075" remote="131872666620000000" Dst="2" />
<file name="away.html" server="O:/intra/portfolio/" local="131872702626151648" remote="131872666620000000" Dst="2" />
<file name="eric.html" server="O:/intra/portfolio/" local="131872702626373334" remote="131872666620000000" Dst="2" />
<file name="kat.html" server="O:/intra/portfolio/" local="131872702626644127" remote="131872666620000000" Dst="2" />
<file name="links.html" server="O:/intra/portfolio/" local="131872702625956455" remote="131872666620000000" Dst="2" />
<file name="other.html" server="O:/intra/portfolio/" local="131872702626834956" remote="131872666620000000" Dst="2" />
</dwsync>